evenage/__init__.py
evenage/llms.py
evenage/api/__init__.py
evenage/api/main.py
evenage/cli/__init__.py
evenage/cli/main.py
evenage/cli/commands/__init__.py
evenage/cli/commands/add.py
evenage/cli/commands/check.py
evenage/cli/commands/infra.py
evenage/cli/commands/init.py
evenage/cli/commands/management.py
evenage/cli/commands/prompt.py
evenage/cli/commands/run.py
evenage/cli/templates/Dockerfile.j2
evenage/cli/templates/README.md.j2
evenage/cli/templates/agent_flat.py.j2
evenage/cli/templates/docker-compose.yml.j2
evenage/cli/templates/dotenv.j2
evenage/cli/templates/main_flat.py.j2
evenage/cli/templates/requirements.txt.j2
evenage/cli/templates/test_tools.py.j2
evenage/cli/templates/tool.py.j2
evenage/cli/templates/tools_communication.py.j2
evenage/cli/templates/tools_web.py.j2
evenage/cli/utils/__init__.py
evenage/cli/utils/config.py
evenage/cli/utils/docker.py
evenage/cli/utils/errors.py
evenage/cli/utils/logger.py
evenage/cli/utils/templates.py
evenage/core/__init__.py
evenage/core/agent_runtime.py
evenage/core/cache.py
evenage/core/config.py
evenage/core/database.py
evenage/core/llm.py
evenage/core/mcp_client.py
evenage/core/message_bus.py
evenage/core/runtime_entry.py
evenage/core/storage.py
evenage/core/system_tools.py
evenage/core/tooling.py
evenage-0.9.3.dist-info/METADATA
evenage-0.9.3.dist-info/WHEEL
evenage-0.9.3.dist-info/entry_points.txt
evenage-0.9.3.dist-info/RECORD
